ckanext/__init__.py
ckanext/search_preset/__init__.py
ckanext/search_preset/config.py
ckanext/search_preset/helpers.py
ckanext/search_preset/plugin.py
ckanext/search_preset/logic/__init__.py
ckanext/search_preset/logic/action.py
ckanext/search_preset/logic/auth.py
ckanext/search_preset/logic/schema.py
ckanext/search_preset/templates/package/read.html
ckanext/search_preset/templates/package/search.html
ckanext/search_preset/templates/search_preset/snippets/add_preset.html
ckanext/search_preset/templates/search_preset/snippets/package_list.html
ckanext/search_preset/templates/search_preset/snippets/preset_section.html
ckanext/search_preset/tests/__init__.py
ckanext/search_preset/tests/conftest.py
ckanext/search_preset/tests/plugin.py
ckanext/search_preset/tests/test_helpers.py
ckanext/search_preset/tests/logic/__init__.py
ckanext/search_preset/tests/logic/test_auth.py
ckanext_search_preset-0.0.1.post1.dist-info/LICENSE
ckanext_search_preset-0.0.1.post1.dist-info/METADATA
ckanext_search_preset-0.0.1.post1.dist-info/WHEEL
ckanext_search_preset-0.0.1.post1.dist-info/entry_points.txt
ckanext_search_preset-0.0.1.post1.dist-info/top_level.txt
ckanext_search_preset-0.0.1.post1.dist-info/RECORD
