Metadata-Version: 2.1
Name: ckanext-search-preset
Version: 0.0.1.post1
Author-email: DataShades <datashades@linkdigital.com.au>, Sergey Motornyuk <sergey.motornyuk@linkdigital.com.au>
Maintainer-email: DataShades <datashades@linkdigital.com.au>
License: AGPL
Project-URL: Homepage, https://github.com/DataShades/ckanext-search-preset
Keywords: CKAN
Classifier: Development Status :: 4 - Beta
Classifier: License :: OSI Approved :: GNU Affero General Public License v3 or later (AGPLv3+)
Classifier: Programming Language :: Python :: 3.7
Classifier: Programming Language :: Python :: 3.8
Classifier: Programming Language :: Python :: 3.9
Classifier: Programming Language :: Python :: 3.10
License-File: LICENSE
Requires-Dist: ckanext-toolbelt >=0.2.5
Requires-Dist: typing-extensions
Provides-Extra: dev
Requires-Dist: pytest-ckan ; extra == 'dev'
Requires-Dist: pytest-factoryboy ; extra == 'dev'
